caai_vllm_tools/__init__.py
caai_vllm_tools/chat.py
caai_vllm_tools-0.1.2.dist-info/METADATA
caai_vllm_tools-0.1.2.dist-info/WHEEL
caai_vllm_tools-0.1.2.dist-info/top_level.txt
caai_vllm_tools-0.1.2.dist-info/RECORD
